[
  {
    "arguments": [
      "/usr/bin/gcc",
      "-g",
      "-std=gnu99",
      "-Wall",
      "-Iinclude",
      "-fPIC",
      "-c",
      "-o",
      "src/library/disk.o",
      "src/library/disk.c"
    ],
    "directory": "/Users/tutu/Desktop/SimpleFS",
    "file": "/Users/tutu/Desktop/SimpleFS/src/library/disk.c",
    "output": "/Users/tutu/Desktop/SimpleFS/src/library/disk.o"
  },
  {
    "arguments": [
      "/usr/bin/gcc",
      "-g",
      "-std=gnu99",
      "-Wall",
      "-Iinclude",
      "-fPIC",
      "-c",
      "-o",
      "src/library/fs.o",
      "src/library/fs.c"
    ],
    "directory": "/Users/tutu/Desktop/SimpleFS",
    "file": "/Users/tutu/Desktop/SimpleFS/src/library/fs.c",
    "output": "/Users/tutu/Desktop/SimpleFS/src/library/fs.o"
  },
  {
    "arguments": [
      "/usr/bin/gcc",
      "-g",
      "-std=gnu99",
      "-Wall",
      "-Iinclude",
      "-fPIC",
      "-c",
      "-o",
      "src/tests/unit_disk.o",
      "src/tests/unit_disk.c"
    ],
    "directory": "/Users/tutu/Desktop/SimpleFS",
    "file": "/Users/tutu/Desktop/SimpleFS/src/tests/unit_disk.c",
    "output": "/Users/tutu/Desktop/SimpleFS/src/tests/unit_disk.o"
  },
  {
    "arguments": [
      "/usr/bin/gcc",
      "-g",
      "-std=gnu99",
      "-Wall",
      "-Iinclude",
      "-fPIC",
      "-c",
      "-o",
      "src/tests/unit_fs.o",
      "src/tests/unit_fs.c"
    ],
    "directory": "/Users/tutu/Desktop/SimpleFS",
    "file": "/Users/tutu/Desktop/SimpleFS/src/tests/unit_fs.c",
    "output": "/Users/tutu/Desktop/SimpleFS/src/tests/unit_fs.o"
  },
  {
    "arguments": [
      "/usr/bin/gcc",
      "-g",
      "-std=gnu99",
      "-Wall",
      "-Iinclude",
      "-fPIC",
      "-c",
      "-o",
      "src/shell/sfssh.o",
      "src/shell/sfssh.c"
    ],
    "directory": "/Users/tutu/Desktop/SimpleFS",
    "file": "/Users/tutu/Desktop/SimpleFS/src/shell/sfssh.c",
    "output": "/Users/tutu/Desktop/SimpleFS/src/shell/sfssh.o"
  }
]
